README.md
setup.py
skBox/DfTool.py
skBox/DocxApi.py
skBox/MailTool.py
skBox/Toolbox.py
skBox/__init__.py
skBox/skLogger.py
skBox.egg-info/PKG-INFO
skBox.egg-info/SOURCES.txt
skBox.egg-info/dependency_links.txt
skBox.egg-info/requires.txt
skBox.egg-info/top_level.txt