Metadata-Version: 2.1
Name: skBox
Version: 0.26.2
Summary: super kit box
Home-page: UNKNOWN
Author: Hanmi Cheng
Author-email: jxmt089659g@163.com
License: UNKNOWN
Platform: UNKNOWN
